{
  "date": "2026-05-02T02:25:31.344858+00:00",
  "version": "20260502",
  "sources": [
    {
      "name": "AdGuard Mobile",
      "rule_count": 8423
    },
    {
      "name": "AdGuard Chinese",
      "rule_count": 21447
    },
    {
      "name": "Chaniug AdSuper",
      "rule_count": 52
    },
    {
      "name": "Adguard Extra",
      "rule_count": 15
    }
  ],
  "stats": {
    "initial_rules": 29937,
    "final_rules": 29894,
    "duplicates": 43,
    "processing_time_sec": 0.150851,
    "checksum": "baa1fe165c6237382fd00e3fef500cd06ba0752803f5553a58bd9c3e24d721e8"
  }
}