{
  "date": "2026-06-09T02:45:11.693893+00:00",
  "version": "20260609",
  "sources": [
    {
      "name": "AdGuard Mobile",
      "rule_count": 8499
    },
    {
      "name": "AdGuard Chinese",
      "rule_count": 21529
    },
    {
      "name": "Chaniug AdSuper",
      "rule_count": 61
    },
    {
      "name": "Adguard Extra",
      "rule_count": 15
    }
  ],
  "stats": {
    "initial_rules": 30104,
    "final_rules": 30058,
    "duplicates": 46,
    "processing_time_sec": 0.163604,
    "checksum": "b41c7c8eac473ef20a3f1b0125c07dc10ba9faad542bc9acdfaab5194f9d8656"
  }
}